wbx_admin_utils/__init__.py
wbx_admin_utils/__main__.py
wbx_admin_utils-1.4.1.dist-info/METADATA
wbx_admin_utils-1.4.1.dist-info/WHEEL
wbx_admin_utils-1.4.1.dist-info/licenses/LICENSE
wbx_admin_utils-1.4.1.dist-info/RECORD
