Metadata-Version: 2.1
Name: wbx_admin_utils
Version: 1.4.1
Summary: A collection of utilities for Webex Control Hub admins and compliance officers
Author-email: Stephane Cohen <stecohen@gmail.com>
License: MIT License
License-File: LICENSE
Keywords: Control Hub,Webex,groups
Classifier: License :: OSI Approved :: MIT License
Classifier: Programming Language :: Python
Classifier: Programming Language :: Python :: 3
Requires-Python: >=3.10
Requires-Dist: pandas
Requires-Dist: requests
